tinytools/__init__.py
tinytools/_version.py
tinytools/bunch.py
tinytools/class_csv.py
tinytools/cmd_line.py
tinytools/diskio.py
tinytools/examples.py
tinytools/files.py
tinytools/np_img.py
tinytools/pvl.py
tinytools/py_styles.py
tinytools/tests/__init__.py
tinytools/tests/test_tinytools.py
tinytools-1.1.1.dist-info/LICENSE.txt
tinytools-1.1.1.dist-info/METADATA
tinytools-1.1.1.dist-info/WHEEL
tinytools-1.1.1.dist-info/top_level.txt
tinytools-1.1.1.dist-info/RECORD
