Metadata-Version: 2.1
Name: tinytools
Version: 1.1.1
Summary: Small, high-level tools that fill gaps in current Python tool sets.
Author: Nathan Longbotham
Author-email: nlongbotham@digitalglobe.com
License-File: LICENSE.txt
Requires-Dist: numpy
